[
	{
		"title": "Start",
		"tags": "",
		"body": "Stanley...\nI'm upset...\nBut you know what would cheer me up..?\nA chocolate cupcake!!\nOh but not just any chocolate cupcake, specially topped with your gorgeous vanilla essence and finished off with rainbow sprinkles!!\nCould you do that.",
		"position": {
			"x": 127,
			"y": 175
		},
		"colorID": 0
	},
	{
		"title": "ReceivedCupcake",
		"tags": "",
		"body": "Let's see...\nThis is exactly what I needed!!\nThanks Stanley!",
		"position": {
			"x": 395,
			"y": 176
		},
		"colorID": 0
	},
	{
		"title": "Node_2",
		"tags": "",
		"body": "Empty Text",
		"position": {
			"x": 641,
			"y": 177
		},
		"colorID": 0
	},
	{
		"title": "Node_3",
		"tags": "",
		"body": "Empty Text",
		"position": {
			"x": -100,
			"y": 416
		},
		"colorID": 0
	}
]